energy_manager/__init__.py
energy_manager/apis/__init__.py
energy_manager/apis/buildings/__init__.py
energy_manager/apis/buildings/get_buildings_consumptions.py
energy_manager/apis/buildings/get_department.py
energy_manager/apis/weather/__init__.py
energy_manager/apis/weather/get_coordinates.py
energy_manager/apis/weather/get_daily_weather.py
energy_manager/apis/weather/get_hourly_weather.py
energy_manager/classes/__init__.py
energy_manager/classes/energy_manager.py
energy_manager/expenses/__init__.py
energy_manager/expenses/compute_daily_expenses.py
energy_manager/utils/__init__.py
energy_manager/utils/data/hchp_hours.csv
energy_manager/utils/generate_daily_timestamps.py
energy_manager/utils/get_midnight_utc_timestamp.py
energy_manager/utils/set_dpe_mappings.py
energy_manager/utils/set_edf_prices.py
energy_manager/utils/set_hchp_hours.py
energy_manager-0.3.4.dist-info/LICENSE
energy_manager-0.3.4.dist-info/METADATA
energy_manager-0.3.4.dist-info/WHEEL
energy_manager-0.3.4.dist-info/RECORD
