Metadata-Version: 2.1
Name: energy_manager
Version: 0.3.4
Summary: A simple tool for French consumers having EDF as energy provider, to give them hints on their houses energy consumption based on seasons !!!
License: MIT
Author: Prince Foli Acouetey
Requires-Python: >=3.12,<4.0
Classifier: License :: OSI Approved :: MIT License
Classifier: Programming Language :: Python :: 3
Classifier: Programming Language :: Python :: 3.12
Classifier: Programming Language :: Python :: 3.13
Requires-Dist: dvc (>=3.57.0,<4.0.0)
Requires-Dist: dvc-s3 (>=3.2.0,<4.0.0)
Requires-Dist: freezegun (>=1.5.1,<2.0.0)
Requires-Dist: matplotlib (>=3.9.3,<4.0.0)
Requires-Dist: pandas (>=2.2.3,<3.0.0)
Requires-Dist: pytest (>=8.3.3,<9.0.0)
Requires-Dist: requests (>=2.32.3,<3.0.0)
Requires-Dist: seaborn (>=0.13.2,<0.14.0)
Requires-Dist: unidecode (>=1.3.8,<2.0.0)
Requires-Dist: urllib3 (<2.0)
